cligv/__init__.py
cligv/alignment.py
cligv/browser.py
cligv/clean.py
cligv/cli.py
cligv/themes.py
cligv/utils.py
cligv-0.1.0.dist-info/licenses/LICENSE.txt
cligv-0.1.0.dist-info/METADATA
cligv-0.1.0.dist-info/WHEEL
cligv-0.1.0.dist-info/entry_points.txt
cligv-0.1.0.dist-info/top_level.txt
cligv-0.1.0.dist-info/RECORD
