Metadata-Version: 2.4
Name: cligv
Version: 0.1.0
Summary: command line Interactive Genome Viewer
Author: Jonas Freudigmann
License: MIT
Project-URL: Homepage, https://github.com/jonasfreudig/cligv
Project-URL: Documentation, https://cligv.readthedocs.io
Project-URL: Bug Tracker, https://github.com/jonasfreudig/cligv/issues
Classifier: Development Status :: 4 - Beta
Classifier: Environment :: Console
Classifier: Intended Audience :: Science/Research
Classifier: License :: OSI Approved :: MIT License
Classifier: Programming Language :: Python :: 3
Classifier: Programming Language :: Python :: 3.7
Classifier: Programming Language :: Python :: 3.8
Classifier: Programming Language :: Python :: 3.9
Classifier: Programming Language :: Python :: 3.10
Classifier: Topic :: Scientific/Engineering :: Bio-Informatics
Requires-Python: >=3.7
License-File: LICENSE.txt
Requires-Dist: pysam>=0.19.0
Requires-Dist: rich>=10.0.0
Dynamic: license-file
